aether/__init__.py
aether/bundler.py
aether/cli.py
aether/entity_helpers.py
aether/inspection.py
aether/introspection.py
aether/mcp_server.py
aether/resolver.py
aether/scaffolding.py
aether/schema.py
aether/schema_scaffolding.py
aether/spec.py
aether/utils.py
aether/validation_context.py
aether/validator.py
jintra_aether-1.0.4.dist-info/entry_points.txt
jintra_aether-1.0.4.dist-info/licenses/LICENSE
jintra_aether-1.0.4.dist-info/METADATA
jintra_aether-1.0.4.dist-info/WHEEL
jintra_aether-1.0.4.dist-info/RECORD
