Metadata-Version: 2.4
Name: jintra-aether
Version: 1.0.4
Summary: A lightweight, extensible framework for structured content authoring and validation with AI assistance
License: FSL-1.1-MIT
License-File: LICENSE
Keywords: schema,validation,content,yaml,json,structured-data
Author: Jayce
Author-email: jayce@jintra.io
Requires-Python: >=3.9
Classifier: Development Status :: 5 - Production/Stable
Classifier: Intended Audience :: Developers
Classifier: License :: Other/Proprietary License
Classifier: Programming Language :: Python :: 3
Classifier: Programming Language :: Python :: 3.9
Classifier: Programming Language :: Python :: 3.10
Classifier: Programming Language :: Python :: 3.11
Classifier: Programming Language :: Python :: 3.12
Classifier: Programming Language :: Python :: 3.13
Classifier: Programming Language :: Python :: 3.14
Classifier: Topic :: Documentation
Classifier: Topic :: Software Development :: Libraries :: Python Modules
Classifier: Topic :: Text Processing :: Markup
Requires-Dist: jsonschema (>=4.25.1,<5.0.0)
Requires-Dist: pyyaml (>=6.0.3,<7.0.0)
Project-URL: Documentation, https://github.com/jintra-jayce/aether
Project-URL: Homepage, https://github.com/jintra-jayce/aether
Project-URL: Repository, https://github.com/jintra-jayce/aether
